drop_duplicates_in_pd_column/__init__.py
drop_duplicates_in_pd_column/drop_dupes.py
drop_duplicates_in_pd_column-0.1.1.dist-info/WHEEL
drop_duplicates_in_pd_column-0.1.1.dist-info/METADATA
drop_duplicates_in_pd_column-0.1.1.dist-info/RECORD
