Metadata-Version: 2.1
Name: drop-duplicates-in-pd-column
Version: 0.1.1
Summary: 
Author: ilikechicken67
Author-email: thomas.staats443@gmail.com
Requires-Python: >=3.7,<4.0
Classifier: Programming Language :: Python :: 3
Classifier: Programming Language :: Python :: 3.7
Classifier: Programming Language :: Python :: 3.8
Classifier: Programming Language :: Python :: 3.9
Requires-Dist: pandas (>=1.0.1,<2.0.0)
